{"message":"success","suppliers":[{"manufacturer_id":"9","code":"001","company_name":"Technofood","contact_name":"Mehdi Bourguiba","phone_number":"22218000","postal_code":"2082 ","city":"Tunis","country":"Tunisia","capital":"Tunis","email":"slim.boughzala@technofoodindustries.com"},{"manufacturer_id":"10","code":"002","company_name":"STIFEN","contact_name":"AHLEM BEN SLIMEN","phone_number":"94856975","city":"Tunis","country":"Tunisie","capital":"Tunis","email":"ahlem.benslimen@stifen.com,"},{"manufacturer_id":"11","code":"003","company_name":"Manar Thon","tax_registration_number":"912362/Y","contact_name":"Oussama Naguez ","phone_number":"26 750 314","city":"Tunis","country":"Tunisie","capital":"Tunis","email":"fact.manarthon@horchani.com"},{"manufacturer_id":"12","code":"004","company_name":"socohuiles","contact_name":"Hacem Kamoun","phone_number":"96460005","city":"Tunis","country":"Tunisie","capital":"Tunis","email":"direction.commerciale@socohuile.com.tn"},{"manufacturer_id":"13","code":"005","company_name":"Société L'Appétissante S.A","contact_name":"TOM","email":"TOM@kamioun.tn"},{"manufacturer_id":"14","code":"006","company_name":"zgolli","email":"hbelkadhi@iffco.com"},{"manufacturer_id":"15","code":"007","company_name":"Cristal Tunisie","email":"hbelkadhi@iffco.com"},{"manufacturer_id":"20","code":"008","company_name":"Tucal","email":"tucal@contact.tn"},{"manufacturer_id":"21","code":"009","company_name":" Hamza maatallah","email":"ourahou.oussama@gmail.com"},{"manufacturer_id":"22","code":"010","company_name":"Sidi Daoud","email":"Abco@kamioun.tn"},{"manufacturer_id":"23","code":"012","company_name":"Société Al Baraka ","email":"makrem@kamioun.tn"},{"manufacturer_id":"24","code":"013","company_name":"ChocoNord","email":"choconord@gmail.com"},{"manufacturer_id":"25","code":"014","company_name":"Ste Alimentaire du Sud","contact_name":"Kif SAS","email":"kif@gmail.tn"},{"manufacturer_id":"26","code":"011","company_name":"Cash & Carry","email":"Cashand carry@gmail.tn"},{"manufacturer_id":"27","code":"015","company_name":"Samir","email":"samiir@gmail.tn"},{"manufacturer_id":"28","code":"016","company_name":"Sapori Italia","contact_name":"Kais Akremi","email":"kais.3akremi@gmail.com"},{"manufacturer_id":"29","code":"017","company_name":"Fnar","email":"khadija@kamioun.tn"},{"manufacturer_id":"30","code":"018","company_name":"Sidi Jebeur","email":"khadija@kamioun.tn"},{"manufacturer_id":"31","code":"019","company_name":"Alliance","contact_name":" Ferid Hajri","city":"Tunis","email":"makrem@kamioun.tn"},{"manufacturer_id":"32","code":"020","company_name":"AZIZA","email":"AZIZA@CONTACT.TN"},{"manufacturer_id":"33","code":"021","company_name":"Soukra Distribution","email":"soukra@test.tn"},{"manufacturer_id":"34","code":"022","company_name":"Om Elkhir","city":"Tunis","email":"malloukaymen@gmail.com"},{"manufacturer_id":"36","code":"023","company_name":"Randa","email":"randa@kamioun.tn"},{"manufacturer_id":"38","code":"0121","company_name":"El Baraka - Vrac","email":"elbaraka@kamioun.tn"},{"manufacturer_id":"39","code":"141","company_name":"SATHOP","city":"Tunis","email":"sathop@kamioun.tn"},{"manufacturer_id":"40","code":"142","company_name":"SOBOCO","email":"soboco@kamioun.tn"},{"manufacturer_id":"41","code":"024","company_name":"Ferid Khemakhem","email":"khemakhem@kamioun.tn"},{"manufacturer_id":"42","code":"025","company_name":"SODET","email":"sodet@kamioun.tn"},{"manufacturer_id":"43","code":"026","company_name":"SOTUCHOC","contact_name":"Mohamed Ben Salah","phone_number":"58551635","email":"Mehrez.Ibrahmi@sotuchoc.com.tn"},{"manufacturer_id":"44","code":"027","company_name":"La brosse","email":"labrosse@kamioun.tn"},{"manufacturer_id":"45","code":"028","company_name":"Gen. Alim","email":"gen.alim@kamioun.tn"},{"manufacturer_id":"46","code":"029","company_name":"Daily'n","email":"dailyn@kamioun.tn"},{"manufacturer_id":"47","code":"030","company_name":"Agrimed","email":"safi@kamioun.tn"},{"manufacturer_id":"48","code":"031","company_name":"Dioline","email":"dioline@kamioun.tn"},{"manufacturer_id":"49","code":"032","company_name":"Aldi","email":"aldi@kamioun.tn"},{"manufacturer_id":"50","code":"033","company_name":"Bondin","contact_name":"Sami Ouenniche","email":"Sami.OUENNICHE@bondin.com "},{"manufacturer_id":"51","code":"034","company_name":"Bonelle Sarl","email":"putemailwhenyoucan@kamioun.tn"},{"manufacturer_id":"52","code":"035","company_name":"Med Oil Company","email":"bnh.slim.medoil@gmail.com"},{"manufacturer_id":"53","code":"036","company_name":"Ulysse Tunisie","phone_number":"98 510 130","email":"Mohamed.Hlali@utic.com.tn"},{"manufacturer_id":"54","code":"037","company_name":"Tunisie Farine","phone_number":"29133719","email":"ghazi.troudi@randa.com.tn"},{"manufacturer_id":"55","code":"038","company_name":"Promocom","phone_number":"27157703","email":"fares.belghith.p@gmail.com"},{"manufacturer_id":"56","code":"039","company_name":"SOTUBI","email":"sotubi"},{"manufacturer_id":"57","code":"040","company_name":"Forma Agro Tunisia SA","contact_name":"Nizar Ben Ammar","phone_number":"93197400","email":"nizar.ben.ammar@ilo.com.tn"},{"manufacturer_id":"58","code":"041","company_name":"El Khabia","contact_name":"Moncef","email":"hamza@kamioun.tn"},{"manufacturer_id":"59","code":"042","company_name":"Dr Nature","contact_name":"Achref","phone_number":"99685985","city":"Sousse","email":"drnature@kamioun.tn"},{"manufacturer_id":"60","code":"043","company_name":"Golden Food","contact_name":"Saber","phone_number":"28149539","email":"goldenfood.tunisie@gmail.com"},{"manufacturer_id":"61","code":"044","company_name":"Sotuchoc Old","contact_name":"Mohamed Ben Salah","phone_number":"58551635","email":"Mehrez.Ibrahmi@sotuchoc.com.tn"},{"manufacturer_id":"62","code":"045","company_name":"Fournisseur eau","contact_name":"Makrem?","email":"test"},{"manufacturer_id":"63","code":"046","company_name":"Fruit de bonte","contact_name":"Achref","phone_number":"‎+216 95 638 108","email":"hela.chaouachi20@gmail.com"},{"manufacturer_id":"64","code":"047","company_name":"LBM","contact_name":"Mohamed Ismail Mokr","email":"LBM@contact.tn"},{"manufacturer_id":"65","code":"048","company_name":"BIC","phone_number":"29118989","email":"developpement@stisnegoce.com"},{"manufacturer_id":"66","code":"050","company_name":"Sicam","email":"sicam@contact.com"},{"manufacturer_id":"67","code":"051","company_name":"Epices Sté Sfax Food","contact_name":"Rafaa","phone_number":"22764449","email":"miladirafaa9@gmail.com"},{"manufacturer_id":"68","code":"052","company_name":"Société CSM-GIAS SA","email":"ahmed.touati@slama.com.tn"},{"manufacturer_id":"69","code":"053","company_name":"STE Meniouni","email":"Notarealemail@kamioun.tn"},{"manufacturer_id":"70","code":"054","company_name":"COMOCAP","phone_number":"98426918","email":"petitparis@planet.tn"},{"manufacturer_id":"71","code":"071","company_name":"Société Nakhil ","tax_registration_number":"1376543/V/P/M/000","contact_name":"Yessine al gati","phone_number":"97198345-23059305","address":"50 Rue jawdat al hayat, chotrana 1 sidi saleh - soukra","postal_code":"2035 ","city":"Ariana","country":"Tunisie","email":"contact@gmail.com"},{"manufacturer_id":"72","code":"072","company_name":"Al Habib","email":"contact@alhabibi.com"},{"manufacturer_id":"73","code":"055","company_name":"SOINDI","phone_number":"29505608","email":"belhassen.assidi@soindi.com"},{"manufacturer_id":"74","code":"073","company_name":"BCB trading Company","email":"contact@bcb.tn"},{"manufacturer_id":"75","code":"074","company_name":"Hop Company","phone_number":"99709000","email":"honeylacommercial@gmail.com"},{"manufacturer_id":"76","code":"075","company_name":"Sté Union Internationale de commerce","contact_name":"Khemais Borsali","phone_number":"98403382","email":"khmaisborsali@gmail.com"},{"manufacturer_id":"77","code":"076","company_name":"Kamioun - Packs","email":"ivy@kamioun.tn"},{"manufacturer_id":"78","code":"077","company_name":"Moulin d'or","email":"allala.zoghbi@moulindor.net"},{"manufacturer_id":"80","code":"078","company_name":"SOKADI","email":"SOKADI@test.com"},{"manufacturer_id":"81","code":"079","company_name":"La Patissiére","tax_registration_number":"00581K/P/M/000","contact_name":"La Patissiere","phone_number":"71808600","address":"23 Rue de l'énergie Z I charguia 1 2035","email":"PATISSIERE@test.tn"},{"manufacturer_id":"82","code":"080","company_name":"Confiserie Triki","tax_registration_number":"004208HAM000","contact_name":"Farid Fazai","phone_number":"28300831","address":"Megrine","postal_code":"22222","city":"Ben arous","country":"Tunisie","capital":"Tunis","email":"faridfazai78@gmail.com"},{"manufacturer_id":"83","code":"081","company_name":"Proxim","tax_registration_number":"1454499W/N/M/000","phone_number":"71206598","address":"Rue sanhaja mutuelle ville 1082 Tunis","postal_code":"1082","email":"Test@test.com"},{"manufacturer_id":"84","code":"084","company_name":"TAS","tax_registration_number":"0620048S/A/M/000","phone_number":"71388714","address":"B.P 187 Ben Arous","email":"test@test.tn"},{"manufacturer_id":"85","code":"085","company_name":"2 S Distribution","tax_registration_number":"1510350R/A/M/000","phone_number":"31367167","postal_code":"2082","city":"mghira","country":"tunis","email":"s.c.d@gnet.tn"},{"manufacturer_id":"86","code":"086","company_name":"Societe Red Go","tax_registration_number":"1422207S/A/M/000","postal_code":"086","email":"TEST@test1.tn"},{"manufacturer_id":"87","code":"087","company_name":"PACO","tax_registration_number":"723520Q/A/M/000","phone_number":"36000656","email":"Paco@planet.tn"},{"manufacturer_id":"88","code":"090","company_name":"Maison du lumiere","tax_registration_number":"1757277/Q/A/M/000","email":"Test@test.tn"},{"manufacturer_id":"89","code":"091","company_name":"Societé Bayt elnour","tax_registration_number":"1757277/Q/A/M/000","email":"test@test.tn"},{"manufacturer_id":"90","code":"092","company_name":"ABCO","tax_registration_number":"0633423P","email":"abco@abco.tn"},{"manufacturer_id":"91","code":"093","company_name":"La Capitale Commerce et distribution","tax_registration_number":"1760248K/N/M/000","email":"la.capitale.distribution@gmail.com"},{"manufacturer_id":"92","code":"094","company_name":"Medfish","tax_registration_number":"1710817/V/A/M/000","email":"Medfish@fish.fish"},{"manufacturer_id":"93","code":"095","company_name":"YMTC","email":"ymtc@ymtc.tn"},{"manufacturer_id":"94","code":"098","company_name":"Biskart","tax_registration_number":"1702462QAM000","email":"biskart@test.tn"},{"manufacturer_id":"95","code":"099","company_name":"","email":"test@test.tn"},{"manufacturer_id":"96","code":"100","company_name":"Asdrubal Distribution","email":"asdrubal.distribution@gmail.com"},{"manufacturer_id":"97","code":"101","company_name":"Ritej","tax_registration_number":"1437414A/A/M/000","email":"steritej@gmail.com"},{"manufacturer_id":"98","code":"102","company_name":"SOTRACO","contact_name":"Dhawaka","email":"www.sotraco.com.tn"},{"manufacturer_id":"99","code":"103","company_name":"Blel Distribution","email":"supplier@test.tn"},{"manufacturer_id":"100","code":"105","company_name":"Bourguiba GOLD10","email":"Bourguibagold10@gmail.com"},{"manufacturer_id":"101","code":"106","company_name":"Societé saniatna ","tax_registration_number":"1604894PAM000","email":"contact@seniatna.com"},{"manufacturer_id":"102","code":"107","company_name":"BK Food","email":"kamiounbkfood@kamioun.tn"},{"manufacturer_id":"103","code":"108","company_name":"Agrimed","email":"agrimed@kamioun.tn"},{"manufacturer_id":"104","code":"109","company_name":"Atlas Trading Group","email":"atlas@kamioun.tn"},{"manufacturer_id":"105","code":"110","company_name":"Ayham Pack","email":"ayhampack@kamioun.tn"},{"manufacturer_id":"106","code":"111","company_name":"damado caffé","email":"damado@kamioun.tn"},{"manufacturer_id":"107","code":"112","company_name":"AMT","email":"amt@kamioun.tn"},{"manufacturer_id":"108","code":"113","company_name":"ECOFISH","email":"ecofish@kamioun.tn"},{"manufacturer_id":"109","code":"114","company_name":"EL GAMRA S.R.L","email":"elgamra@kamioun.tn"},{"manufacturer_id":"110","code":"115","company_name":"IFFCO","email":"iffco@kamioun.tn"},{"manufacturer_id":"111","code":"116","company_name":"L'Orient","email":"orient@kamioun.tn"},{"manufacturer_id":"112","code":"117","company_name":"Grossiste","email":"grossiste@kamioun.tn"},{"manufacturer_id":"113","code":"118","company_name":"LAPEC Distribution","email":"lapec@kamioun.tn"},{"manufacturer_id":"114","code":"119","company_name":"Sté Mag Distribution","email":"magdistribution@kamioun.tn"},{"manufacturer_id":"115","code":"120","company_name":"Markis Food","email":"markisfood@kamioun.tn"},{"manufacturer_id":"116","code":"121","company_name":"Mokador","email":"mokador@kamioun.tn"},{"manufacturer_id":"117","code":"122","company_name":"OCT","email":"oct@kamioun.tn"},{"manufacturer_id":"118","code":"123","company_name":"Warda Pates","email":"warda@kamioun.tn"},{"manufacturer_id":"119","code":"124","company_name":"Soboco old","email":"sobocco@kamioun.tn"},{"manufacturer_id":"120","code":"125","company_name":"Marchaoui","email":"marchaoui@kamioun.tn"},{"manufacturer_id":"121","code":"126","company_name":"Délice","email":"Délice@kamioun.tn"},{"manufacturer_id":"122","code":"218","company_name":"Karkwen","email":"karkwen@kamioun.tn"},{"manufacturer_id":"123","code":"300","company_name":"Mondial Kaki","email":"mondial-kaki@kamioun.tn"},{"manufacturer_id":"124","code":"301","company_name":"al rayan","email":"rayan@kamioun.tn"},{"manufacturer_id":"125","code":"302","company_name":"SKY Edition Distribution","email":"Sky-distribution@kamioun.tn"},{"manufacturer_id":"126","code":"303","company_name":"Délice","email":"303"},{"manufacturer_id":"127","code":"304","company_name":"Loisir","email":"304"},{"manufacturer_id":"128","code":"1111","company_name":"Bind Food","email":"qjlfdbs@nsdq.dsq"},{"manufacturer_id":"129","code":"2222","company_name":"SMPA","email":"dailyn@kamioun.tn"},{"manufacturer_id":"130","code":"230","company_name":"Essafa","email":"alsafa@kamioun.tn"},{"manufacturer_id":"131","code":"235","company_name":"Dokrem","email":"Dokrem@kamioun.tn"},{"manufacturer_id":"132","code":"233","company_name":"FLAVOR FOOD","email":"FLAVOR FOOD@kamioun.tn"},{"manufacturer_id":"133","code":"350","company_name":"STE HAZEM","email":"HAZEM SIROP@kamioun.tn"},{"manufacturer_id":"134","code":"351","company_name":"Beroplast","email":"Romeo@kamioun.tn"},{"manufacturer_id":"135","code":"144","company_name":"Loisir","email":"loisir@kamioun.tn"},{"manufacturer_id":"136","code":"1000","company_name":"LBP","email":"LBP@kamioun.tn"},{"manufacturer_id":"137","code":"255","company_name":"Mondial de Commerce Zyan","email":"zyan@kamioun.tn"},{"manufacturer_id":"138","code":"352","company_name":"Etinarme+","tax_registration_number":"1458644D/A/M/000","phone_number":"71940201","email":"contact@etinarme.com"},{"manufacturer_id":"139","code":"127","company_name":"Epices Smaoui","email":"kamioun@kamioun.tn"},{"manufacturer_id":"140","code":"353","company_name":"Ste Ben Ayed Du Commerce","tax_registration_number":"1089758H/A/M/000","phone_number":"70684744","address":"1 rue 7214 Chautrana 1 - Soukra - 2036 Ariana","postal_code":"2036","city":"Ariana ","country":"Tunisia","email":"sbcnovacafe@gmail.com"},{"manufacturer_id":"141","code":"354","company_name":"Smart Distribution ","tax_registration_number":"1535875A/A/M/000","contact_name":"Marwen Ben Abdlmlak","phone_number":"98104090","address":"Ariana Supérieur","postal_code":"2080","city":"Ariana","country":"Tunisia","email":"Smart@smart-tn.com"},{"manufacturer_id":"142","code":"128","company_name":"Société Gias Distribution","email":"kamioun@kamioun.tn"},{"manufacturer_id":"143","code":"129","company_name":"Société Gias Industries","email":"kamioun@kamioun.tn"},{"manufacturer_id":"144","code":"130","company_name":"Dr Oetker Gias Commercial","email":"kamioun@kamioun.tn"},{"manufacturer_id":"145","code":"356","company_name":"z&ZIZOO","tax_registration_number":"1600988C/A/M/000","contact_name":"Z&ZIZOO","phone_number":"98699973","address":"Z.I BIRINE SIDI HSSINE","postal_code":"1095","city":"TUNIS","country":"TUNISIA","email":"z.zizou@gnet.tn"},{"manufacturer_id":"146","code":"357","company_name":"Tradisco","tax_registration_number":"798816P/A/M/000","contact_name":"Tradisco","phone_number":"79408980","address":"128 Rue De Béja Z.I MGHIRA 2-2082 FOUCHENA","postal_code":"2082","city":"BEN AROUS","country":"TUNISIA","email":"TRADISCO@GNET.TN"},{"manufacturer_id":"147","code":"358","company_name":"Ste Aymen Ben Ayed","tax_registration_number":"136666W/P/M/000","contact_name":"Ben Ayed ","phone_number":"58588101","address":"Ain sobeh chotrana 1 - Soukra ","postal_code":"2036","city":"Ariana","country":"Tunisia","email":"cafebenayed2014@gmail.com"},{"manufacturer_id":"148","code":"360","company_name":"Ste Stipav","tax_registration_number":"1461212G/A/M/000","contact_name":"Khaled ","phone_number":"71864688","address":"126 AV.13 Aout Chotrana 2 La Soukra","city":"Ariana","country":"Tunisia","email":"ste.stpav@gmail.com"},{"manufacturer_id":"149","code":"361","company_name":"Ste B.H.B","tax_registration_number":"1744558D/P/M/000","contact_name":"khaled","phone_number":"71864699","address":"126 AV. 13 Aout Chotrana 2 La Soukra ","city":"Ariana","country":"Tunisia","email":"bhb.direction@gmail.com"},{"manufacturer_id":"150","code":"370","company_name":"Spipa","tax_registration_number":"001558Q/A/M/000","contact_name":"Raouf Maaref ","phone_number":"20500508","address":"21 rue 8601 - la Charguia - 2035 Tunis ","postal_code":"2035","city":"TUNIS","country":"TUNISIA","email":"contact@spipa.com.tn"},{"manufacturer_id":"151","code":"371","company_name":"BBK Pack ","tax_registration_number":"1806091/A/M/000","contact_name":"Ahmed Ben Brahim","phone_number":"28384990","address":"Rue Hawel Elwed 6000 Gabes ","postal_code":"6000","city":"Gabes","country":"Tunisia","email":"BBKPACK@GMAIL.COM"},{"manufacturer_id":"152","code":"380","company_name":"COJED","tax_registration_number":"960132/D/A/C/000","contact_name":"Jemni Mondher ","phone_number":"71491180","address":"103 RUE 9042 JEBEL JELOUD TUNIS ","city":"TUNIS","country":"TUNISIA","email":"COJED@GMAIL.COM"},{"manufacturer_id":"153","code":"390","company_name":"Kunuz","tax_registration_number":"1788250/Z/A/E/001","phone_number":"31559456","address":"Cité el bassetine bouha, Mornaguia ","postal_code":"5000","city":"Mornaguia","country":"Tunisia","capital":"Tunis","email":"Kunuz.agroalimentaire@gmail.com"},{"manufacturer_id":"154","code":"391","company_name":"Ste Les Abattoirs Chahia","tax_registration_number":"14904413B/M/P/000","contact_name":"Issam Zguir","phone_number":"27970440","address":"Route sidi salem km 1.5 ","postal_code":"3003","city":"SFAX","country":"TUNISIA","email":"issam.zguir@gmail.com"},{"manufacturer_id":"155","code":"392","company_name":"BVM","contact_name":"AHMED","phone_number":"71385005","address":"Zone industrielle bir kasaa  ","postal_code":"2013","city":"BEN AROUS","country":"TUNISIA","email":"bvm@bvm.com.tn"},{"manufacturer_id":"156","code":"393","company_name":"neptus","tax_registration_number":"1705943/R/P/M/000","contact_name":"SAIDA ","phone_number":"79408779","address":"Z.I MGHIRA 2 LOT N°57","postal_code":"2082","city":"FOUCHANA","country":"TUNISIA","email":"commercial.neptus@colorPack-International.com"},{"manufacturer_id":"157","code":"394","company_name":"SICA MILED ABIDA","contact_name":"HAITHEM","phone_number":"25934013","address":"ROUTE DU  KEF KM3 DAHMENI","postal_code":"7170","city":"KEF","country":"TINISIA","email":"MILED_ABIDA@HEXABYTE.TN"},{"manufacturer_id":"158","code":"397","company_name":"SGIA MIRA","tax_registration_number":"1185848Y/A/M/000","phone_number":"31336060","address":"27 AVENUE TAIEB MHIRI 2080 ARIANA ","postal_code":"2080","city":"ARIANA","country":"TUNISIA","email":"marwen@kamioun.tn"},{"manufacturer_id":"159","code":"395","company_name":"Société Lemar Trading","tax_registration_number":"1691825L/P/M/000","contact_name":"Nassim Donia","phone_number":"54650434","address":"Route de sousse 5160 el Jem ","postal_code":"5160","city":"MAHDIA","country":"TUNISIA","email":"Marwen@kamioun.tn"},{"manufacturer_id":"160","code":"396","company_name":"Société Federal Distribution ","tax_registration_number":"1683012H/A/M/000","contact_name":"NASSIM","phone_number":"54650434","address":"ROUTE DE SOUSSE 5160 EL JEM","postal_code":"5160","city":"MAHDIA","country":"TUNISIA","email":"MARWEN@KAMIOUN.TN"},{"manufacturer_id":"161","code":"400","company_name":"Société Al Baraka ","tax_registration_number":"1553580/P/A/M/000","contact_name":"Kais","phone_number":"70608020","address":"Route de sousse - Eljem - Mahdia","city":"MAHDIA","country":"TUNISIA","email":"Hello@albarakaplus.com"},{"manufacturer_id":"162","code":"401","company_name":"Snackee Food Company","tax_registration_number":"1705943/R/P/M/000","contact_name":"Anis","phone_number":"20 50 55 98","address":"Cité 15 octobre, route de kalaat al andaloss ","postal_code":"2061","city":"ariana","country":"tunisia","email":"contact@weepops.com"},{"manufacturer_id":"163","code":"402","company_name":"Ste Generale des boissons et des industries Alimentaires (SGBIA)","tax_registration_number":"307017K/A/M/000","contact_name":"Ali","phone_number":"71385133","address":"KM 6 ROUTE DE SOUSSE Z.I 2013 BEN AROUS ","postal_code":"2013","city":"BEN AROUS","country":"TUNISIA","capital":"TUNIS","email":"marwen@kamioun.tn"},{"manufacturer_id":"164","code":"405","company_name":"Fruit & Co","tax_registration_number":"1820141/J","contact_name":"MALEK HATTAB","phone_number":"54873525","address":"CITE MANFALOUTI","postal_code":"1100","city":"ZAGHOUEN","country":"TUNIS","capital":"TUNIS","email":"abdelmalekhatab@gmail.com"},{"manufacturer_id":"165","code":"500","company_name":"FAIZA MANSOUR DES AFFAIRES DE COMMERCE ","tax_registration_number":"1816717/Z/M/P/000","contact_name":"El 7aj","phone_number":"51624444","address":"043 khaireddine pacha, mnihla","postal_code":"2092","city":"Ariana","country":"Tunisia","email":"marwen@kamioun.tn"},{"manufacturer_id":"166","code":"501","company_name":"UNPA","tax_registration_number":"1705943/R/P/M/000","contact_name":"Soufien","phone_number":"29630011","address":"Avenue Habib Mellouli ","postal_code":"4002","city":"Sousse","country":"Tunisia","capital":"Tunisia","email":"Commercial.gms@lepidor.com.tn"},{"manufacturer_id":"167","code":"502","company_name":"Snacks Tunisia","contact_name":"KAIS","phone_number":"95590538","address":"sa","city":"tunis","email":"kais.jebril@mad-chips.com"},{"manufacturer_id":"168","code":"503","company_name":"STE LAVENDEL KEKS","tax_registration_number":"1826583/J","contact_name":"Hatem Jebali","address":"cite khlij boumhal","city":"TUNIS","email":"hatem.jebali007@gmail.com"},{"manufacturer_id":"169","code":"505","company_name":"Lavendel","tax_registration_number":"1826583/J/A/M/000","phone_number":"71216485","email":"lavende.keks.tunesia@gmail.com"},{"manufacturer_id":"170","code":"506","company_name":"UNI FOOD ","tax_registration_number":"1531335/H","contact_name":"MOHAMED","phone_number":"55368926","address":"ZRIBA","email":"mohamedunifood@gmail.com"},{"manufacturer_id":"172","code":"0510","company_name":"Monia Slama","tax_registration_number":"1428979/J/N/C/000","contact_name":"Monia Slama","phone_number":"25520678","address":"Nour Jaafer","city":"ARIANA","country":"TUNISIA","email":"marwen@kamioun.tn"},{"manufacturer_id":"173","code":"511","company_name":"Hejer Pour La Vente et la Distribution","tax_registration_number":"0134562023C","contact_name":"GAHZI TROUDI ","phone_number":"29133719","address":"عدد19 نهج الحبيب عاشور المنزه1 1004 المنزه","email":"Troudiz@gmail.com"},{"manufacturer_id":"174","code":"512","company_name":"STEM","tax_registration_number":"1638452ZAM000","contact_name":"TIBA","phone_number":"71138000","address":"KASSERINE ","postal_code":"1240","city":"TUNIS","email":"bmarwen@kamioun.tn"},{"manufacturer_id":"175","code":"513","company_name":"STE MEDIEN FRERE","tax_registration_number":"1676704/N/A/M/000","contact_name":"chokri","phone_number":"20085506","address":"oued el lil","email":"societemadienfreres@gmail.com"},{"manufacturer_id":"176","code":"514","company_name":"MAJDOUB DISTRIBUTIONS","tax_registration_number":"1705943RP/M/000","contact_name":"khaled","phone_number":"22608573","email":"bmarwen@kamioun.tn"},{"manufacturer_id":"177","code":"515","company_name":"mag détergent ","contact_name":"zahra ","phone_number":"29550987","email":"bmarwen@kamioun.tn"},{"manufacturer_id":"178","code":"516","company_name":"CAC DG","tax_registration_number":"1668051/B/P/E/000","contact_name":"agence wed elil","address":"wed elili ","email":"cacdg.commercial@gmail.com"},{"manufacturer_id":"179","code":"517","company_name":"Bona Carthage distribution bonafe cartha  ","tax_registration_number":"1840043/T","address":"OUED ELILI","city":"OUED ELIL","email":"bmarwen@kamioun.tn"},{"manufacturer_id":"180","code":"518","company_name":"PHYTOMED","tax_registration_number":"1131988QAM000","contact_name":"adnen","phone_number":"50691561","address":"MORNEG","email":"COMMERCIAL@VAHNIA.COM"},{"manufacturer_id":"181","code":"519","company_name":"IAT ","tax_registration_number":"610325pam000","phone_number":"58600413","email":"bmarwen@kamioun.tn"},{"manufacturer_id":"182","code":"520","company_name":"KAWAFEL ALKHAYER","contact_name":"nizar","phone_number":"72659625","email":"KAWEFEL@SFB-AGROALIMENTAIRE.COM"},{"manufacturer_id":"183","code":"521","company_name":"LANDOR","tax_registration_number":"1705943RPM000","contact_name":"Makrem","phone_number":"53796155","email":"www.landor.com.tn"},{"manufacturer_id":"184","code":"522","company_name":"SATEM DISTRIBUTION","contact_name":"HICHEM","email":"bmarwen@kamioun.tn"},{"manufacturer_id":"185","code":"523","company_name":"Caravan","contact_name":"anis","address":"sfax","email":"bmarwen@kamioun.tn"},{"manufacturer_id":"186","code":"524","company_name":"societe zoghbi distribution ","tax_registration_number":"1680382V/A/M/000","email":"benhmida.marwen@yahoo.com"},{"manufacturer_id":"187","code":"525","company_name":"MONSAPO","contact_name":"GHADA","phone_number":"98118647","email":"benhmida.marwen@yahoo.com"},{"manufacturer_id":"188","code":"1709","company_name":"COG Morouj","tax_registration_number":"1865170/H/A/M/000","contact_name":"Mourad Oueslati","address":"34 B.AV De la Republique Morouj 3 ","city":"Bn arous ","country":"Tunis ","capital":"Tunisia","email":"marwen@kamioun.tn"},{"manufacturer_id":"189","code":"526","company_name":"beauty secrets","email":"bmarwen@kamioun.tn"},{"manufacturer_id":"190","code":"527","company_name":" apogee distribution","email":"benhmida.marwen@yahoo.com"},{"manufacturer_id":"191","code":"528","company_name":"Ste Hammouda Trading","email":"bmarwen@kamioun.tn"},{"manufacturer_id":"192","code":"3009","company_name":"Ste Hammouda Trading","tax_registration_number":"1585445/H/N/E/002","phone_number":"92142135 / 52875400 ","address":"000 route mahdia , el jem","postal_code":"5160","city":"el jem","country":"tunisia","email":"marwen@kamioun.tn"},{"manufacturer_id":"193","code":"0310","company_name":"Société Ben Njima Sousse","tax_registration_number":"1739855/B/P/M/0000000/T/D/C/000","phone_number":"22104947/54591893","address":"Sousse","postal_code":"4000","city":"sousse","country":"tunisia","capital":"Tunis","email":"marwen@kamioun.tn"},{"manufacturer_id":"194","code":"529","company_name":"TARALLI PRODUCTION ","email":"bmarwen@kamioun.tn"},{"manufacturer_id":"195","code":"1510","company_name":" Minoterie et semoulerie de l'avenue Sadok Bey","tax_registration_number":"1064/X/P/M/000","email":" Minoterie.Sadok Bey@gmail.com"}]}